tests/__init__.py
tests/base.py
tests/test_version.py
xlart/__init__.py
xlart/cli.py
xlart/version.py
xlart-0.1.1.dist-info/DESCRIPTION.rst
xlart-0.1.1.dist-info/METADATA
xlart-0.1.1.dist-info/RECORD
xlart-0.1.1.dist-info/WHEEL
xlart-0.1.1.dist-info/entry_points.txt
xlart-0.1.1.dist-info/metadata.json
xlart-0.1.1.dist-info/top_level.txt
