Metadata-Version: 2.0
Name: xlart
Version: 0.1.1
Summary: Excel art generator
Home-page: https://github.com/ayvazj/xlart
Author: James Ayvaz
Author-email: james.ayvaz@gmail.com
License: MIT
Keywords: excel pixel art
Platform: UNKNOWN
Classifier: Development Status :: 4 - Beta
Classifier: Intended Audience :: Developers
Classifier: License :: OSI Approved :: MIT License
Classifier: Natural Language :: English
Classifier: Operating System :: Unix
Classifier: Programming Language :: Python :: 2.7
Classifier: Programming Language :: Python :: 3.4
Classifier: Programming Language :: Python :: Implementation :: PyPy
Classifier: Operating System :: OS Independent
Requires-Dist: openpyxl (>=2.4.1)
Requires-Dist: Pillow (>=3.4.2)
Provides-Extra: tests
Requires-Dist: mock; extra == 'tests'
Requires-Dist: nose; extra == 'tests'
Requires-Dist: coverage; extra == 'tests'
Requires-Dist: yanc; extra == 'tests'
Requires-Dist: preggy; extra == 'tests'
Requires-Dist: tox; extra == 'tests'
Requires-Dist: ipdb; extra == 'tests'
Requires-Dist: coveralls; extra == 'tests'
Requires-Dist: sphinx; extra == 'tests'
